{
    "roles": {
        "client": {
            "nodedriver": "imp.ImpInProcessNodeDriver",
            "parameters": null
        },
        "server": {
            "nodedriver": "saas.SaasFediverseNodeDriver",
            "parameters": {
                "app": "Takahē",
                "hostname": "gotosocial.social",
                "existing-account-uri": "acct:admin@gotosocial.social",
                "nonexisting-account-uri": "acct:does-not-exist@gotosocial.social"
            }
        }
    },
    "name": "Takahē"
}