{
    "roles": {
        "client": {
            "nodedriver": "imp.ImpInProcessNodeDriver",
            "parameters": null
        },
        "server": {
            "nodedriver": "saas.SaasFediverseNodeDriver",
            "parameters": {
                "app": "Wildebeest",
                "hostname": "cloudflare.social",
                "existing-account-uri": "acct:gargron@cloudflare.social",
                "nonexisting-account-uri": "acct:does-not-exist@cloudflare.social"
            }
        }
    },
    "name": "Wildebeest"
}